LICENSE
fenkeysmanagement/__init__.py
fenkeysmanagement-1.0.1.dist-info/entry_points.txt
fenkeysmanagement-1.0.1.dist-info/LICENSE
fenkeysmanagement-1.0.1.dist-info/WHEEL
fenkeysmanagement-1.0.1.dist-info/METADATA
fenkeysmanagement-1.0.1.dist-info/RECORD
