Metadata-Version: 2.1
Name: fenkeysmanagement
Version: 1.0.1
Summary: Simple key management. Generate tokens for any usage.
Home-page: https://github.com/brodokk/FenKeysManagement
License: GPL-3.0-only
Author: brodokk
Author-email: brodokk@brodokk.space
Requires-Python: >=3.7,<4.0
Classifier: License :: OSI Approved :: GNU General Public License v3 (GPLv3)
Classifier: Programming Language :: Python :: 3
Classifier: Programming Language :: Python :: 3.10
Classifier: Programming Language :: Python :: 3.7
Classifier: Programming Language :: Python :: 3.8
Classifier: Programming Language :: Python :: 3.9
Requires-Dist: tabulate (>=0.8.10,<0.9.0)
Project-URL: Repository, https://github.com/brodokk/FenKeysManagement
